{
  "range_lambdas": {
    "F64": 0.26380773551611236
  },
  "max_lambdas": {
    "F64": 0.5238282052143478
  },
  "pj_mtx_original_dim": {
    "OptionUsize": null
  },
  "min_lambdas": {
    "F64": 0.26002046969823545
  },
  "cluster_radius": {
    "F64": 1.31122581304085
  },
  "nitems": {
    "Usize": 30
  },
  "pj_mtx_reduced_dim": {
    "OptionUsize": null
  },
  "nfeatures": {
    "Usize": 8
  },
  "extra_reduced_dim": {
    "Bool": false
  },
  "taumode": {
    "TauMode": "Median"
  },
  "pj_mtx_seed": {
    "OptionU64": null
  },
  "n_clusters": {
    "Usize": 2
  }
}